[
    {
      "nim": "1234",
      "nama": "Firman Naufal Aryaputra",
      "alamat": "Semarang",
      "jurusan": "Teknik Informatika",
      "MK": [
        {
          "mk_kode": "101",
          "nama_mk": "SISTEM BASIS DATA"
        },
        {
          "mk_kode": "102",
          "nama_mk": "ALJABAR LINIER"
        },
        {
          "mk_kode": "103",
          "nama_mk": "ANALISA ALGORITMA"
        },
        {
          "mk_kode": "104",
          "nama_mk": "KECERDASAN BUATAN"
        },
        {
          "mk_kode": "105",
          "nama_mk": "JARINGAN KOMPUTER"
        }
      ]
    },
    {
      "nim": "1236",
      "nama": "Syifa",
      "alamat": "Pati",
      "jurusan": "Sistem Informasi",
      "MK": [
        {
          "mk_kode": "301",
          "nama_mk": "ANALISA PROSES BISNIS"
        },
        {
          "mk_kode": "302",
          "nama_mk": "DATABASE TERDISTRIBUSI"
        },
        {
          "mk_kode": "303",
          "nama_mk": "ETIKA PROFESI"
        },
        {
          "mk_kode": "304",
          "nama_mk": "REKAYASA WEB"
        },
        {
          "mk_kode": "305",
          "nama_mk": "AUDIT SISTEM INFORMASI"
        }
      ]
    }
  ]